steamfront/__init__.py
steamfront/app.py
steamfront/client.py
steamfront/errors.py
steamfront/exceptions.py
steamfront/game.py
steamfront/steamfront.py
steamfront/user.py
steamfront/userapp.py
steamfront/usergame.py
steamfront-0.1.0.dist-info/DESCRIPTION.rst
steamfront-0.1.0.dist-info/METADATA
steamfront-0.1.0.dist-info/RECORD
steamfront-0.1.0.dist-info/WHEEL
steamfront-0.1.0.dist-info/metadata.json
steamfront-0.1.0.dist-info/top_level.txt
