Metadata-Version: 2.0
Name: steamfront
Version: 0.1.0
Summary: A simple plugin to allow you to nicely access things on the Steam API and web server.
Home-page: https://github.com/4Kaylum/Steamfront
Author: Callum Bartlett
Author-email: callum.b@techie.com
License: mit
Download-URL: https://github.com/4Kaylum/Steamfront/tarball/0.1.0
Keywords: steam web steamfront steampowered
Platform: UNKNOWN
Classifier: Development Status :: 3 - Alpha
Classifier: Intended Audience :: Developers
Classifier: Topic :: Games/Entertainment
Classifier: Topic :: Internet
Classifier: Topic :: Utilities
Classifier: License :: OSI Approved :: MIT License
Classifier: Programming Language :: Python :: 2
Classifier: Programming Language :: Python :: 3
Requires-Dist: requests
